<T3DataStructure>
  <sheets>
    <sDEF>
      <ROOT>
        <TCEforms>
          <sheetTitle>LLL:EXT:marit_references/Resources/Private/Language/locallang_db.xml:tx_maritreferences_flexform.sheet1</sheetTitle>
        </TCEforms>
        <type>array</type>
        <el>
          <switchableControllerActions>
            <TCEforms>
              <label>LLL:EXT:marit_references/Resources/Private/Language/locallang_db.xml:tx_maritreferences_flexform.view</label>
              <config>
                <type>select</type>
                <size>1</size>
                <items typ3="array">
                  <numIndex index="0" type="array">
                    <numIndex index="0">LLL:EXT:marit_references/Resources/Private/Language/locallang_db.xml:tx_maritreferences_flexform.view.I.0</numIndex>
                    <numIndex index="1">Project->list;Project->show;Technology->list;Technology->show;Customer->list;Customer->show</numIndex>
                  </numIndex>                  
                  <numIndex index="1" type="array">
                    <numIndex index="0">LLL:EXT:marit_references/Resources/Private/Language/locallang_db.xml:tx_maritreferences_flexform.view.I.1</numIndex>
                    <numIndex index="1">Project->search</numIndex>
                  </numIndex>              
                  <numIndex index="2" type="array">
                    <numIndex index="0">LLL:EXT:marit_references/Resources/Private/Language/locallang_db.xml:tx_maritreferences_flexform.view.I.2</numIndex>
                    <numIndex index="1">Project->doublebox</numIndex>
                  </numIndex>           
                  <numIndex index="3" type="array">
                    <numIndex index="0">LLL:EXT:marit_references/Resources/Private/Language/locallang_db.xml:tx_maritreferences_flexform.view.I.3</numIndex>
                    <numIndex index="1">Project->contextbox</numIndex>
                  </numIndex>
                </items>
              </config>
            </TCEforms>
          </switchableControllerActions>
        </el>
      </ROOT>
    </sDEF>
    <contextboxOptions>
    	<ROOT>
        <TCEforms>
          <sheetTitle>LLL:EXT:marit_references/Resources/Private/Language/locallang_db.xml:tx_maritreferences_flexform.contextboxOptions</sheetTitle>
        </TCEforms>
        <type>array</type>
        <el>
        	<settings.project.contextbox.projects>
        		<TCEforms>
        			<label>LLL:EXT:marit_references/Resources/Private/Language/locallang_db.xml:tx_maritreferences_flexform.contextboxOptions.projects</label>
        			<config>
        				<type>select</type>
        				<size>10</size>
								<minitems>0</minitems>
								<maxitems>9999</maxitems>
								<autoSizeMax>0</autoSizeMax>
								<multiple>1</multiple>
								<allowed>tx_maritreferences_domain_model_project</allowed>
								<foreign_table>tx_maritreferences_domain_model_project</foreign_table>
        			</config>
        		</TCEforms>
        	</settings.project.contextbox.projects>
        </el>
      </ROOT>
    </contextboxOptions>
    <!--
    <projectOptions>
    	<ROOT>
        <TCEforms>
          <sheetTitle>LLL:EXT:marit_references/Resources/Private/Language/locallang_db.xml:tx_maritreferences_flexform.projectOptions</sheetTitle>
        </TCEforms>
        <type>array</type>
        <el>
        	<title>
        		<TCEforms>
        			<label>LLL:EXT:marit_references/Resources/Private/Language/locallang_db.xml:tx_maritreferences_flexform.projectOptions.listOptions</label>
        			<config>
        				<type>none</type>
        				<size>1</size>
        			</config>
        		</TCEforms>
        	</title>
					<settings.flexform.project.list.image.file.maxW>
						<TCEforms>
							<label>LLL:EXT:marit_references/Resources/Private/Language/locallang_db.xml:tx_maritreferences_flexform.projectOptions.listOptions.imgWidth</label>
							<config>
								<type>input</type>
								<size>8</size>
								<max>5</max>
								<eval>trim</eval>
							</config>
						</TCEforms>
					</settings.flexform.project.list.image.file.maxW>
					<settings.flexform.project.list.lightboxImage.file.maxW>
						<TCEforms>
							<label>LLL:EXT:marit_references/Resources/Private/Language/locallang_db.xml:tx_maritreferences_flexform.projectOptions.listOptions.lightboxImgWidth</label>
							<config>
								<type>input</type>
								<size>8</size>
								<max>5</max>
								<eval>trim</eval>
							</config>
						</TCEforms>
					</settings.flexform.project.list.lightboxImage.file.maxW>
					<settings.flexform.project.list.lightboxImage.file.maxH>
						<TCEforms>
							<label>LLL:EXT:marit_references/Resources/Private/Language/locallang_db.xml:tx_maritreferences_flexform.projectOptions.listOptions.lightboxImgHeight</label>
							<config>
								<type>input</type>
								<size>8</size>
								<max>5</max>
								<eval>trim</eval>
							</config>
						</TCEforms>							
					</settings.flexform.project.list.lightboxImage.file.maxH>
					<settings.flexform.project.list.pageBrowser.maxItems>
						<TCEforms>
							<label>LLL:EXT:marit_references/Resources/Private/Language/locallang_db.xml:tx_maritreferences_flexform.projectOptions.listOptions.maxItems</label>
							<config>
								<type>input</type>
								<size>8</size>
								<max>5</max>
								<eval>trim</eval>
							</config>
						</TCEforms>
					</settings.flexform.project.list.pageBrowser.maxItems> 
        	<title2>
        		<TCEforms>
        			<label>LLL:EXT:marit_references/Resources/Private/Language/locallang_db.xml:tx_maritreferences_flexform.projectOptions.showOptions</label>
        			<config>
        				<type>none</type>
        				<size>1</size>
        			</config>
        		</TCEforms>
        	</title2>
					<settings.flexform.project.show.image.file.maxW>
						<TCEforms>
							<label>LLL:EXT:marit_references/Resources/Private/Language/locallang_db.xml:tx_maritreferences_flexform.projectOptions.showOptions.imgWidth</label>
							<config>
								<type>input</type>
								<size>8</size>
								<max>5</max>
								<eval>trim</eval>
							</config>
						</TCEforms>
					</settings.flexform.project.show.image.file.maxW> 
					<settings.flexform.project.show.lightboxImage.file.maxW>
						<TCEforms>
							<label>LLL:EXT:marit_references/Resources/Private/Language/locallang_db.xml:tx_maritreferences_flexform.projectOptions.showOptions.lightboxImgWidth</label>
							<config>
								<type>input</type>
								<size>8</size>
								<max>5</max>
								<eval>trim</eval>
							</config>
						</TCEforms>
					</settings.flexform.project.show.lightboxImage.file.maxW>
					<settings.flexform.project.show.lightboxImage.file.maxH>
						<TCEforms>
							<label>LLL:EXT:marit_references/Resources/Private/Language/locallang_db.xml:tx_maritreferences_flexform.projectOptions.showOptions.lightboxImgHeight</label>
							<config>
								<type>input</type>
								<size>8</size>
								<max>5</max>
								<eval>trim</eval>
							</config>
						</TCEforms>							
					</settings.flexform.project.show.lightboxImage.file.maxH>
        	<title3>
        		<TCEforms>
        			<label>LLL:EXT:marit_references/Resources/Private/Language/locallang_db.xml:tx_maritreferences_flexform.projectOptions.searchOptions</label>
        			<config>
        				<type>none</type>
        				<size>1</size>
        			</config>
        		</TCEforms>
        	</title3>
        </el>
      </ROOT>
    </projectOptions>
    <customerOptions>
    	<ROOT>
        <TCEforms>
          <sheetTitle>LLL:EXT:marit_references/Resources/Private/Language/locallang_db.xml:tx_maritreferences_flexform.customerOptions</sheetTitle>
        </TCEforms>
        <type>array</type>
        <el>     
					<title>
        		<TCEforms>
        			<label>LLL:EXT:marit_references/Resources/Private/Language/locallang_db.xml:tx_maritreferences_flexform.customerOptions.listOptions</label>
        			<config>
        				<type>none</type>
        				<size>1</size>
        			</config>
        		</TCEforms>
        	</title>
					<settings.flexform.customer.list.image.file.maxW>
						<TCEforms>
							<label>LLL:EXT:marit_references/Resources/Private/Language/locallang_db.xml:tx_maritreferences_flexform.customerOptions.listOptions.imgWidth</label>
							<config>
								<type>input</type>
								<size>8</size>
								<max>5</max>
								<eval>trim</eval>
							</config>
						</TCEforms>
					</settings.flexform.customer.list.image.file.maxW>
					<settings.flexform.customer.list.lightboxImage.file.maxW>
						<TCEforms>
							<label>LLL:EXT:marit_references/Resources/Private/Language/locallang_db.xml:tx_maritreferences_flexform.customerOptions.listOptions.lightboxImgWidth</label>
							<config>
								<type>input</type>
								<size>8</size>
								<max>5</max>
								<eval>trim</eval>
							</config>
						</TCEforms>
					</settings.flexform.customer.list.lightboxImage.file.maxW>
					<settings.flexform.customer.list.lightboxImage.file.maxH>
						<TCEforms>
							<label>LLL:EXT:marit_references/Resources/Private/Language/locallang_db.xml:tx_maritreferences_flexform.customerOptions.listOptions.lightboxImgHeight</label>
							<config>
								<type>input</type>
								<size>8</size>
								<max>5</max>
								<eval>trim</eval>
							</config>
						</TCEforms>							
					</settings.flexform.customer.list.lightboxImage.file.maxH>
					<settings.flexform.customer.list.pageBrowser.maxItems>
						<TCEforms>
							<label>LLL:EXT:marit_references/Resources/Private/Language/locallang_db.xml:tx_maritreferences_flexform.customerOptions.listOptions.maxItems</label>
							<config>
								<type>input</type>
								<size>8</size>
								<max>5</max>
								<eval>trim</eval>
							</config>
						</TCEforms>
					</settings.flexform.customer.list.pageBrowser.maxItems>   
					<settings.flexform.customer.list.description.crop>
						<TCEforms>
							<label>LLL:EXT:marit_references/Resources/Private/Language/locallang_db.xml:tx_maritreferences_flexform.customerOptions.listOptions.cropDescription</label>
							<config>
								<type>input</type>
								<size>8</size>
								<max>5</max>
								<eval>trim</eval>
							</config>
						</TCEforms>
					</settings.flexform.customer.list.description.crop>   
        	<title2>
        		<TCEforms>
        			<label>LLL:EXT:marit_references/Resources/Private/Language/locallang_db.xml:tx_maritreferences_flexform.customerOptions.showOptions</label>
        			<config>
        				<type>none</type>
        				<size>1</size>
        			</config>
        		</TCEforms>
        	</title2>
					<settings.flexform.customer.show.image.file.maxW>
						<TCEforms>
							<label>LLL:EXT:marit_references/Resources/Private/Language/locallang_db.xml:tx_maritreferences_flexform.customerOptions.showOptions.imgWidth</label>
							<config>
								<type>input</type>
								<size>8</size>
								<max>5</max>
								<eval>trim</eval>
							</config>
						</TCEforms>
					</settings.flexform.customer.show.image.file.maxW> 
					<settings.flexform.customer.show.lightboxImage.file.maxW>
						<TCEforms>
							<label>LLL:EXT:marit_references/Resources/Private/Language/locallang_db.xml:tx_maritreferences_flexform.customerOptions.showOptions.lightboxImgWidth</label>
							<config>
								<type>input</type>
								<size>8</size>
								<max>5</max>
								<eval>trim</eval>
							</config>
						</TCEforms>
					</settings.flexform.customer.show.lightboxImage.file.maxW>
					<settings.flexform.customer.show.lightboxImage.file.maxH>
						<TCEforms>
							<label>LLL:EXT:marit_references/Resources/Private/Language/locallang_db.xml:tx_maritreferences_flexform.customerOptions.showOptions.lightboxImgHeight</label>
							<config>
								<type>input</type>
								<size>8</size>
								<max>5</max>
								<eval>trim</eval>
							</config>
						</TCEforms>							
					</settings.flexform.customer.show.lightboxImage.file.maxH>
        </el>
      </ROOT>
    </customerOptions>
    <technologyOptions>
    	<ROOT>
        <TCEforms>
          <sheetTitle>LLL:EXT:marit_references/Resources/Private/Language/locallang_db.xml:tx_maritreferences_flexform.technologyOptions</sheetTitle>
        </TCEforms>
        <type>array</type>
        <el>				
					<title>
        		<TCEforms>
        			<label>LLL:EXT:marit_references/Resources/Private/Language/locallang_db.xml:tx_maritreferences_flexform.technologyOptions.listOptions</label>
        			<config>
        				<type>none</type>
        				<size>1</size>
        			</config>
        		</TCEforms>
        	</title>
					<settings.flexform.technology.list.image.file.maxW>
						<TCEforms>
							<label>LLL:EXT:marit_references/Resources/Private/Language/locallang_db.xml:tx_maritreferences_flexform.technologyOptions.listOptions.imgWidth</label>
							<config>
								<type>input</type>
								<size>8</size>
								<max>5</max>
								<eval>trim</eval>
							</config>
						</TCEforms>
					</settings.flexform.technology.list.image.file.maxW>
					<settings.flexform.technology.list.lightboxImage.file.maxW>
						<TCEforms>
							<label>LLL:EXT:marit_references/Resources/Private/Language/locallang_db.xml:tx_maritreferences_flexform.technologyOptions.listOptions.lightboxImgWidth</label>
							<config>
								<type>input</type>
								<size>8</size>
								<max>5</max>
								<eval>trim</eval>
							</config>
						</TCEforms>
					</settings.flexform.technology.list.lightboxImage.file.maxW>
					<settings.flexform.technology.list.lightboxImage.file.maxH>
						<TCEforms>
							<label>LLL:EXT:marit_references/Resources/Private/Language/locallang_db.xml:tx_maritreferences_flexform.technologyOptions.listOptions.lightboxImgHeight</label>
							<config>
								<type>input</type>
								<size>8</size>
								<max>5</max>
								<eval>trim</eval>
							</config>
						</TCEforms>							
					</settings.flexform.technology.list.lightboxImage.file.maxH>
					<settings.flexform.technology.list.pageBrowser.maxItems>
						<TCEforms>
							<label>LLL:EXT:marit_references/Resources/Private/Language/locallang_db.xml:tx_maritreferences_flexform.technologyOptions.listOptions.maxItems</label>
							<config>
								<type>input</type>
								<size>8</size>
								<max>5</max>
								<eval>trim</eval>
							</config>
						</TCEforms>
					</settings.flexform.technology.list.pageBrowser.maxItems>    
					<settings.flexform.technology.list.description.crop>
						<TCEforms>
							<label>LLL:EXT:marit_references/Resources/Private/Language/locallang_db.xml:tx_maritreferences_flexform.technologyOptions.listOptions.cropDescription</label>
							<config>
								<type>input</type>
								<size>8</size>
								<max>5</max>
								<eval>trim</eval>
							</config>
						</TCEforms>
					</settings.flexform.technology.list.description.crop>    
        	<title2>
        		<TCEforms>
        			<label>LLL:EXT:marit_references/Resources/Private/Language/locallang_db.xml:tx_maritreferences_flexform.technologyOptions.showOptions</label>
        			<config>
        				<type>none</type>
        				<size>1</size>
        			</config>
        		</TCEforms>
        	</title2>
					<settings.flexform.technology.show.image.file.maxW>
						<TCEforms>
							<label>LLL:EXT:marit_references/Resources/Private/Language/locallang_db.xml:tx_maritreferences_flexform.technologyOptions.showOptions.imgWidth</label>
							<config>
								<type>input</type>
								<size>8</size>
								<max>5</max>
								<eval>trim</eval>
							</config>
						</TCEforms>
					</settings.flexform.technology.show.image.file.maxW> 
					<settings.flexform.technology.show.lightboxImage.file.maxW>
						<TCEforms>
							<label>LLL:EXT:marit_references/Resources/Private/Language/locallang_db.xml:tx_maritreferences_flexform.technologyOptions.showOptions.lightboxImgWidth</label>
							<config>
								<type>input</type>
								<size>8</size>
								<max>5</max>
								<eval>trim</eval>
							</config>
						</TCEforms>
					</settings.flexform.technology.show.lightboxImage.file.maxW>
					<settings.flexform.technology.show.lightboxImage.file.maxH>
						<TCEforms>
							<label>LLL:EXT:marit_references/Resources/Private/Language/locallang_db.xml:tx_maritreferences_flexform.technologyOptions.showOptions.lightboxImgHeight</label>
							<config>
								<type>input</type>
								<size>8</size>
								<max>5</max>
								<eval>trim</eval>
							</config>
						</TCEforms>							
					</settings.flexform.technology.show.lightboxImage.file.maxH>
        </el>
      </ROOT>
    </technologyOptions>
    -->
  </sheets>
</T3DataStructure>